aia_utils/Queue.py
aia_utils/__init__.py
aia_utils/http/aia_http.py
aia_utils/img_utils.py
aia_utils/logs_cfg.py
aia_utils/manifest.py
aia_utils/model/aia_model.py
aia_utils/mqtt.py
aia_utils/repositories/aia_msg_repo.py
aia_utils/repositories/aia_semantic_repo.py
aia_utils/toml_utils.py
aia_utils-0.4.7.dist-info/METADATA
aia_utils-0.4.7.dist-info/WHEEL
aia_utils-0.4.7.dist-info/RECORD
