Metadata-Version: 2.3
Name: aia_utils
Version: 0.4.7
Summary: 
Author: Edgar Sánchez
Author-email: edgar.sanchez@mercadolibre.cl
Requires-Python: >=3.11,<4.0
Classifier: Programming Language :: Python :: 3
Classifier: Programming Language :: Python :: 3.11
Classifier: Programming Language :: Python :: 3.12
Classifier: Programming Language :: Python :: 3.13
Requires-Dist: PyYAML (>=6.0.1,<7.0.0)
Requires-Dist: confluent-kafka (>=2.5.3,<3.0.0)
Requires-Dist: coverage (>=7.3.2,<8.0.0)
Requires-Dist: html2image (>=2.0.4,<3.0.0)
Requires-Dist: paho-mqtt (>=2.1.0,<3.0.0)
Requires-Dist: pillow (>=10.2.0,<11.0.0)
Requires-Dist: pymongo (>=4.6.1,<5.0.0)
Requires-Dist: requests (>=2.32.3,<3.0.0)
Requires-Dist: tomli (>=2.0.1,<3.0.0)
